CHANGELOG.rst
LICENSE
MANIFEST.in
README.rst
setup.py
LittleHTTPServer.egg-info/PKG-INFO
LittleHTTPServer.egg-info/SOURCES.txt
LittleHTTPServer.egg-info/dependency_links.txt
LittleHTTPServer.egg-info/entry_points.txt
LittleHTTPServer.egg-info/top_level.txt
littlehttpserver/LittleHTTPServer.py
littlehttpserver/__init__.py
littlehttpserver/__main__.py
littlehttpserver/tests/test_parser.py
littlehttpserver/tests/test_utils_env.py
littlehttpserver/utils/__init__.py
littlehttpserver/utils/env.py