Metadata-Version: 1.1
Name: LittleHTTPServer
Version: 0.5.0
Summary: Little bit extended SimpleHTTPServer
Home-page: https://bitbucket.org/t2y/littlehttpserver
Author: Tetsuya Morimoto
Author-email: tetsuya dot morimoto at gmail dot com
License: Apache License 2.0
Keywords: http,server,document
Platform: unix
Platform: linux
Platform: osx
Classifier: Development Status :: 4 - Beta
Classifier: Environment :: Web Environment
Classifier: Intended Audience :: Developers
Classifier: Operating System :: MacOS :: MacOS X
Classifier: Operating System :: POSIX
Classifier: Programming Language :: Python
Classifier: Programming Language :: Python :: 2.7
Classifier: Programming Language :: Python :: 3
Classifier: Programming Language :: Python :: 3.2
Classifier: Programming Language :: Python :: 3.3
Classifier: Programming Language :: Python :: 3.4
Classifier: Programming Language :: Python :: 3.5
Classifier: Topic :: Internet :: WWW/HTTP :: Dynamic Content
Classifier: Topic :: Software Development :: Testing
Classifier: Topic :: Software Development
Classifier: Topic :: Utilities
